{
  "name": "Project Singularity",
  "dark": {
    "h": 265,
    "c": 40,
    "l": 10,
    "overrides": {
      "--color-gray-50": "#e6e0ff",
      "--color-gray-100": "#ccc2ff",
      "--color-gray-200": "#9985ff",
      "--color-gray-300": "#6647ff",
      "--color-gray-400": "#330aff",
      "--color-gray-500": "#1a00e6",
      "--color-gray-600": "#1300b3",
      "--color-gray-700": "#0c0080",
      "--color-gray-800": "#080033",
      "--color-gray-850": "#04001a",
      "--color-gray-900": "#02000d",
      "--color-gray-950": "#010005"
    },
    "customCSS": "/* --- PROJECT SINGULARITY: VOID INTERFACE --- */\n@keyframes phase-shift {\n  0% { transform: translate(0); }\n  20% { transform: translate(-1px, 1px); }\n  40% { transform: translate(-1px, -1px); }\n  60% { transform: translate(1px, 1px); }\n  80% { transform: translate(1px, -1px); }\n  100% { transform: translate(0); }\n}\n\n/* Cosmic Grain Texture */\nbody::after {\n\tcontent: '';\n\tposition: fixed;\n\ttop: 0; left: 0; width: 100%; height: 100%;\n\topacity: 0.04;\n\tz-index: 9998;\n\tpointer-events: none;\n\tbackground-image: url(\"data:image/svg+xml,%3Csvg viewBox='0 0 200 200' xmlns='http://www.w3.org/2000/svg'%3E%3Cfilter id='noiseFilter'%3E%3CfeTurbulence type='fractalNoise' baseFrequency='0.65' numOctaves='3' stitchTiles='stitch'/%3E%3C/filter%3E%3Crect width='100%25' height='100%25' filter='url(%23noiseFilter)'/%3E%3C/svg%3E\");\n}\n\n/* Cherenkov Glow Prose */\n.prose h1, .prose h2, .prose h3 {\n\tcolor: #00f2ff !important;\n\ttext-shadow: 0 0 15px rgba(0, 242, 255, 0.4);\n\ttext-transform: uppercase;\n\tletter-spacing: 2px;\n}\n\n/* Singularity Inputs */\ninput, textarea, .bg-gray-850 {\n\tbackground-color: rgba(2, 0, 13, 0.8) !important;\n\tborder: 1px solid #330aff !important;\n\tborder-radius: 0px !important;\n\tbox-shadow: inset 0 0 20px rgba(51, 10, 255, 0.1);\n\tfont-family: 'JetBrains Mono', monospace !important;\n}\n\n/* Kinetic Toggles (Buttons) */\nbutton.bg-blue-500, button.bg-blue-600, .btn-primary {\n\tbackground: #00f2ff !important;\n\tcolor: #010005 !important;\n\tborder-radius: 0px !important;\n\tfont-weight: 900 !important;\n\tborder: none !important;\n\tclip-path: polygon(10% 0, 100% 0, 90% 100%, 0% 100%);\n\ttransition: all 0.2s;\n}\n\nbutton.bg-blue-500:hover {\n\tanimation: phase-shift 0.2s infinite;\n\tbackground: #fff !important;\n\tbox-shadow: 0 0 30px rgba(0, 242, 255, 0.6) !important;\n}\n\n/* Sidebar Void */\n#sidebar {\n\tborder-right: 1px solid rgba(51, 10, 255, 0.3) !important;\n\tbackground-color: rgba(1, 0, 5, 0.9) !important;\n}",
    "customCssEnabled": true,
    "autoScope": true,
    "locks": {
      "--color-gray-50": true,
      "--color-gray-100": true,
      "--color-gray-200": true,
      "--color-gray-300": true,
      "--color-gray-400": true,
      "--color-gray-500": true,
      "--color-gray-600": true,
      "--color-gray-700": true,
      "--color-gray-800": true,
      "--color-gray-850": true,
      "--color-gray-900": true,
      "--color-gray-950": true
    },
    "canvasEnabled": true,
    "canvasScript": "/**\n * Title: Gravitational Accretion\n * Description: High-speed particles orbiting the singularity (mouse).\n */\n\nconst CONFIG = {\n    particleCount: 400,\n    starColor: 'rgba(0, 242, 255, 0.5)',\n    singularityColor: 'rgba(255, 255, 255, 0.8)',\n    gravity: 0.05,\n    friction: 0.96\n};\n\nlet canvas, ctx, w, h;\nlet particles = [];\nlet mouse = { x: -5000, y: -5000 };\n\nsetInterval(() => self.postMessage({ type: 'heartbeat' }), 1000);\n\nself.onmessage = (e) => {\n    if (e.data.type === 'init') {\n        canvas = e.data.canvas; ctx = canvas.getContext('2d');\n        resize(e.data.width, e.data.height);\n        render();\n    } else if (e.data.type === 'resize') {\n        resize(e.data.width, e.data.height);\n    } else if (e.data.type === 'mousemove') {\n        mouse.x = e.data.x; mouse.y = e.data.y;\n    }\n};\n\nfunction resize(width, height) {\n    w = width; h = height;\n    if (canvas) { canvas.width = w; canvas.height = h; }\n    particles = [];\n    for (let i = 0; i < CONFIG.particleCount; i++) {\n        particles.push({\n            x: Math.random() * w,\n            y: Math.random() * h,\n            vx: (Math.random() - 0.5) * 10,\n            vy: (Math.random() - 0.5) * 10,\n            size: Math.random() * 1.5 + 0.5\n        });\n    }\n}\n\nfunction render() {\n    if (!ctx) return;\n    ctx.clearRect(0, 0, w, h);\n\n    for (let p of particles) {\n        let dx = mouse.x - p.x;\n        let dy = mouse.y - p.y;\n        let dist = Math.hypot(dx, dy);\n        \n        if (dist < 1000) {\n            let force = (1000 - dist) / 1000;\n            p.vx += (dx / dist) * force * CONFIG.gravity * 20;\n            p.vy += (dy / dist) * force * CONFIG.gravity * 20;\n        }\n\n        p.x += p.vx;\n        p.y += p.vy;\n        p.vx *= CONFIG.friction;\n        p.vy *= CONFIG.friction;\n\n        // Draw Singularity Pull\n        ctx.fillStyle = dist < 50 ? CONFIG.singularityColor : CONFIG.starColor;\n        ctx.fillRect(p.x, p.y, p.size, p.size);\n\n        if (p.x < 0 || p.x > w || p.y < 0 || p.y > h) {\n            p.x = Math.random() * w;\n            p.y = Math.random() * h;\n            p.vx = 0; p.vy = 0;\n        }\n    }\n    requestAnimationFrame(render);\n}",
    "canvasShowAuth": true,
    "themeShowAuth": true,
    "customCssShowAuth": true
  },
  "light": {
    "h": 265,
    "c": 5,
    "l": 95,
    "overrides": {
      "--color-gray-950": "#010005",
      "--color-gray-900": "#08003d",
      "--color-gray-850": "#0c0066",
      "--color-gray-800": "#1300a3",
      "--color-gray-700": "#1a00cc",
      "--color-gray-600": "#330aff",
      "--color-gray-500": "#6647ff",
      "--color-gray-400": "#9985ff",
      "--color-gray-300": "#c2b8ff",
      "--color-gray-200": "#ddd6ff",
      "--color-gray-100": "#ece8ff",
      "--color-gray-50": "#f5f2ff"
    },
    "customCSS": "/* Singularity Light: Minimal High-Tech Paper */\nbutton.bg-blue-500 {\n\tclip-path: polygon(10% 0, 100% 0, 90% 100%, 0% 100%);\n\tbackground: #000 !important;\n\tcolor: #fff !important;\n}",
    "customCssEnabled": true,
    "autoScope": true,
    "locks": {},
    "canvasEnabled": true,
    "canvasScript": "/** Gravitational Accretion Light */\nconst CONFIG = { particleCount: 100, starColor: 'rgba(0, 0, 0, 0.1)' };",
    "canvasShowAuth": true,
    "themeShowAuth": true,
    "customCssShowAuth": true
  },
  "oled": {
    "h": 265,
    "c": 40,
    "l": 0,
    "overrides": {
      "--color-gray-950": "#000000",
      "--color-gray-900": "#000000",
      "--color-gray-850": "#02000a",
      "--color-gray-800": "#05001a",
      "--color-gray-700": "#0c004d",
      "--color-gray-600": "#130080",
      "--color-gray-500": "#1a00e6",
      "--color-gray-400": "#330aff",
      "--color-gray-300": "#6647ff",
      "--color-gray-200": "#9985ff",
      "--color-gray-100": "#ccc2ff",
      "--color-gray-50": "#ffffff"
    },
    "customCSS": "/* PROJECT SINGULARITY (OLED) */\nbody::after { opacity: 0.08; } /* Visible noise on OLED */\n.prose h1 { text-shadow: 0 0 25px #00f2ff; }\ninput, textarea { border-color: #00f2ff !important; }",
    "customCssEnabled": true,
    "autoScope": true,
    "locks": {
      "--color-gray-50": true,
      "--color-gray-100": true,
      "--color-gray-200": true,
      "--color-gray-300": true,
      "--color-gray-400": true,
      "--color-gray-500": true,
      "--color-gray-600": true,
      "--color-gray-700": true,
      "--color-gray-800": true,
      "--color-gray-850": true,
      "--color-gray-900": true,
      "--color-gray-950": true
    },
    "canvasEnabled": true,
    "canvasScript": "/** Gravitational Accretion OLED */\nconst CONFIG = { particleCount: 600, starColor: 'rgba(0, 242, 255, 0.8)', gravity: 0.08 };",
    "canvasShowAuth": true,
    "themeShowAuth": true,
    "customCssShowAuth": true
  },
  "her": {
    "h": 320,
    "c": 30,
    "l": 95,
    "overrides": {
      "--color-gray-950": "#1a0020",
      "--color-gray-900": "#33004d",
      "--color-gray-850": "#4d0073",
      "--color-gray-800": "#660099",
      "--color-gray-700": "#9900cc",
      "--color-gray-600": "#cc00ff",
      "--color-gray-500": "#e066ff",
      "--color-gray-400": "#eeaaff",
      "--color-gray-300": "#f5ccff",
      "--color-gray-200": "#f9e0ff",
      "--color-gray-100": "#fcf0ff",
      "--color-gray-50": "#fef8ff"
    },
    "customCSS": "/* Singularity Nebula Mode */\n.prose h1 { color: #ff00ff !important; text-shadow: 0 0 10px #ff00ff; }\nbutton.bg-blue-500 { background: #ff00ff !important; }",
    "customCssEnabled": true,
    "autoScope": true,
    "locks": {},
    "canvasEnabled": true,
    "canvasScript": "/** Gravitational Accretion Her */\nconst CONFIG = { particleCount: 300, starColor: 'rgba(255, 0, 255, 0.3)' };",
    "canvasShowAuth": true,
    "themeShowAuth": true,
    "customCssShowAuth": true
  },
  "updateUrl": "https://raw.githubusercontent.com/silentoplayz/theme-designer-pro-presets/main/themes/project_singularity.json",
  "version": "1.0.0",
  "author": "silentoplayz (G30)",
  "description": "Void interface with gravitational distortion effects, Accretion Canvas FX, and deep violet-black tones with phase-shift animations.",
  "repositoryUrl": "https://github.com/silentoplayz/theme-designer-pro-presets",
  "targetVersion": "0.9.0"
}
